README.md
setup.cfg
setup.py
urnai/__init__.py
urnai/__main__.py
urnai/urnai_cmd.py
urnai.egg-info/PKG-INFO
urnai.egg-info/SOURCES.txt
urnai.egg-info/dependency_links.txt
urnai.egg-info/entry_points.txt
urnai.egg-info/requires.txt
urnai.egg-info/top_level.txt
urnai/agents/__init__.py
urnai/agents/generic_agent.py
urnai/agents/sc2_agent.py
urnai/agents/actions/__init__.py
urnai/agents/actions/gym_wrapper.py
urnai/agents/actions/ple_wrapper.py
urnai/agents/actions/sc2.py
urnai/agents/actions/sc2_wrapper.py
urnai/agents/actions/vizdoom_wrapper.py
urnai/agents/actions/base/__init__.py
urnai/agents/actions/base/abwrapper.py
urnai/agents/base/__init__.py
urnai/agents/base/abagent.py
urnai/agents/rewards/__init__.py
urnai/agents/rewards/abreward.py
urnai/agents/rewards/default.py
urnai/agents/rewards/gym.py
urnai/agents/rewards/sc2.py
urnai/agents/rewards/vizdoom.py
urnai/agents/states/__init__.py
urnai/agents/states/abstate.py
urnai/agents/states/gym.py
urnai/agents/states/ple.py
urnai/agents/states/sc2.py
urnai/agents/states/vizdoom.py
urnai/base/__init__.py
urnai/base/savable.py
urnai/envs/__init__.py
urnai/envs/deep_rts.py
urnai/envs/gym.py
urnai/envs/gym_2048.py
urnai/envs/mini_rts.py
urnai/envs/ple.py
urnai/envs/sc2.py
urnai/envs/vizdoom.py
urnai/envs/base/__init__.py
urnai/envs/base/abenv.py
urnai/models/__init__.py
urnai/models/ddqn_keras.py
urnai/models/dql_keras.py
urnai/models/dql_keras_mem.py
urnai/models/dql_tf.py
urnai/models/dql_tf_flexible.py
urnai/models/model_builder.py
urnai/models/pg_tf.py
urnai/models/ql_table.py
urnai/models/base/__init__.py
urnai/models/base/abmodel.py
urnai/runner/__init__.py
urnai/runner/commands.py
urnai/runner/parserbuilder.py
urnai/runner/runnerbuilder.py
urnai/runner/base/__init__.py
urnai/runner/base/runner.py
urnai/scenarios/__init__.py
urnai/scenarios/base/__init__.py
urnai/scenarios/base/abscenario.py
urnai/scenarios/generalization/__init__.py
urnai/scenarios/generalization/rts/__init__.py
urnai/scenarios/generalization/rts/collectables.py
urnai/tdd/__init__.py
urnai/tdd/reporter.py
urnai/trainers/__init__.py
urnai/trainers/jsontrainer.py
urnai/trainers/trainer.py
urnai/utils/__init__.py
