Metadata-Version: 1.0
Name: urnai
Version: 0.0.2
Summary: A modular Deep Reinforcement Learning library that supports multiple environments, such as PySC2, OpenAI Gym, and PyGame Learning Environment.
Home-page: https://github.com/marcocspc/URNAI-Tools
Author: UFRN-IMD-URNAITeam
Author-email: urnaiteam@gmail.com
License: UNKNOWN
Platform: UNKNOWN
